{
   "Head": [
      "60",
      "65",
      "50",
      "5",
      "0",
      "0",
      "5",
      "10",
      "100",
      "100"
   ],
   "Neck": [
      "45",
      "40",
      "45",
      "10",
      "0",
      "0",
      "5",
      "5",
      "0",
      "100"
   ],
   "Stomach": [
      "40",
      "60",
      "50",
      "10",
      "0",
      "0",
      "5",
      "10",
      "0",
      "100"
   ],
   "Back": [
      "30",
      "30",
      "45",
      "10",
      "0",
      "0",
      "5",
      "10",
      "0",
      "100"
   ],
   "Tail": [
      "40",
      "35",
      "30",
      "10",
      "0",
      "0",
      "5",
      "15",
      "0",
      "100"
   ],
   "Forelegs": [
      "65",
      "55",
      "30",
      "5",
      "0",
      "0",
      "5",
      "10",
      "0",
      "100"
   ],
   "Hindlegs": [
      "25",
      "25",
      "25",
      "5",
      "0",
      "0",
      "5",
      "5",
      "0",
      "100"
   ],
   "Wings": [
      "35",
      "35",
      "30",
      "10",
      "0",
      "0",
      "5",
      "15",
      "0",
      "100"
   ],
   "Headwater": [
      "40",
      "40",
      "25",
      "40",
      "0",
      "0",
      "15",
      "30",
      "100",
      "100"
   ],
   "Neckwater": [
      "25",
      "25",
      "40",
      "25",
      "0",
      "0",
      "10",
      "15",
      "0",
      "100"
   ],
   "Stomachwater": [
      "30",
      "45",
      "45",
      "20",
      "0",
      "0",
      "15",
      "15",
      "0",
      "100"
   ],
   "Backwater": [
      "25",
      "25",
      "30",
      "30",
      "0",
      "0",
      "10",
      "20",
      "0",
      "100"
   ],
   "Tailwater": [
      "25",
      "25",
      "25",
      "25",
      "0",
      "0",
      "10",
      "15",
      "0",
      "100"
   ],
   "Forelegswater": [
      "45",
      "35",
      "20",
      "10",
      "0",
      "0",
      "15",
      "10",
      "0",
      "100"
   ],
   "Hindlegswater": [
      "20",
      "20",
      "20",
      "10",
      "0",
      "0",
      "5",
      "5",
      "0",
      "100"
   ],
   "Wingswater": [
      "25",
      "25",
      "20",
      "30",
      "5",
      "0",
      "20",
      "20",
      "0",
      "100"
   ]
}