{
   "Horns": [
      "20",
      "25",
      "35",
      "5",
      "15",
      "15",
      "0",
      "20",
      "100",
      "100"
   ],
   "Hornsbroken": [
      "35",
      "40",
      "45",
      "5",
      "15",
      "15",
      "0",
      "20",
      "100",
      "100"
   ],
   "Head": [
      "45",
      "60",
      "45",
      "5",
      "10",
      "10",
      "15",
      "15",
      "100",
      "100"
   ],
   "Stomach": [
      "35",
      "30",
      "35",
      "0",
      "0",
      "10",
      "5",
      "10",
      "0",
      "100"
   ],
   "Back": [
      "30",
      "35",
      "30",
      "0",
      "0",
      "10",
      "5",
      "10",
      "0",
      "100"
   ],
   "Forearms": [
      "50",
      "45",
      "40",
      "5",
      "5",
      "15",
      "0",
      "15",
      "0",
      "100"
   ],
   "Hindlegs": [
      "35",
      "30",
      "35",
      "0",
      "0",
      "10",
      "5",
      "10",
      "0",
      "100"
   ],
   "Wings": [
      "40",
      "30",
      "30",
      "10",
      "5",
      "10",
      "5",
      "10",
      "0",
      "100"
   ],
   "Tail": [
      "45",
      "35",
      "25",
      "10",
      "5",
      "10",
      "5",
      "10",
      "0",
      "100"
   ],
   "Tailtip": [
      "45",
      "35",
      "25",
      "15",
      "5",
      "15",
      "5",
      "15",
      "0",
      "100"
   ],
   "Headwhite": [
      "75",
      "90",
      "60",
      "5",
      "10",
      "15",
      "15",
      "15",
      "100",
      "100"
   ],
   "Headblack": [
      "20",
      "25",
      "15",
      "5",
      "10",
      "20",
      "15",
      "20",
      "100",
      "100"
   ],
   "Forearmswhite": [
      "70",
      "60",
      "55",
      "5",
      "5",
      "15",
      "0",
      "15",
      "0",
      "100"
   ],
   "Forearmsblack": [
      "20",
      "25",
      "15",
      "15",
      "5",
      "15",
      "5",
      "20",
      "0",
      "100"
   ],
   "Wingswhite": [
      "55",
      "45",
      "45",
      "10",
      "5",
      "10",
      "5",
      "15",
      "0",
      "100"
   ],
   "Wingsblack": [
      "28",
      "25",
      "25",
      "10",
      "5",
      "15",
      "5",
      "20",
      "0",
      "100"
   ],
   "Tailtipwhite": [
      "65",
      "55",
      "45",
      "15",
      "5",
      "15",
      "5",
      "15",
      "0",
      "100"
   ],
   "Tailtipblack": [
      "10",
      "15",
      "15",
      "5",
      "5",
      "15",
      "0",
      "20",
      "0",
      "100"
   ]
}